lego_handlers/__init__.py
lego_handlers/components.py
lego_handlers/py.typed
lego_handlers-1.1.4.dist-info/METADATA
lego_handlers-1.1.4.dist-info/WHEEL
lego_handlers-1.1.4.dist-info/RECORD
